meraxes/finance/__init__.py
meraxes/finance/admin.py
meraxes/finance/models.py
meraxes/finance/serializer.py
meraxes/finance/urls.py
meraxes/finance/views.py
meraxes/finance/migrations/0001_initial.py
meraxes/finance/migrations/__init__.py
meraxes.finance-0.2.1a0.dist-info/METADATA
meraxes.finance-0.2.1a0.dist-info/WHEEL
meraxes.finance-0.2.1a0.dist-info/top_level.txt
meraxes.finance-0.2.1a0.dist-info/RECORD
